qaboard/__init__.py
qaboard/__main__.py
qaboard/api.py
qaboard/bit_accuracy.py
qaboard/check_for_updates.py
qaboard/ci_helpers.py
qaboard/compat.py
qaboard/config.py
qaboard/conventions.py
qaboard/git.py
qaboard/gitlab.py
qaboard/init.py
qaboard/iterators.py
qaboard/optimize.py
qaboard/qa.py
qaboard/qa_aggregate.py
qaboard/run.py
qaboard/utils.py
qaboard/runners/__init__.py
qaboard/runners/base.py
qaboard/runners/celery.py
qaboard/runners/celery_app.py
qaboard/runners/jenkins_windows.py
qaboard/runners/job.py
qaboard/runners/local.py
qaboard/runners/lsf.py
qaboard/sample_project/qaboard.yaml
qaboard/sample_project/qa/batches.yaml
qaboard/sample_project/qa/main.py
qaboard/sample_project/qa/metrics.yaml
qatools/__init__.py
qaboard-1.0.1.dist-info/LICENSE
qaboard-1.0.1.dist-info/METADATA
qaboard-1.0.1.dist-info/WHEEL
qaboard-1.0.1.dist-info/entry_points.txt
qaboard-1.0.1.dist-info/top_level.txt
qaboard-1.0.1.dist-info/RECORD
