Metadata-Version: 2.1
Name: qaboard
Version: 1.0.1
Summary: Visualize and compare algorithm results. Optimize parameters. Share results and track progress.
Home-page: https://github.com/Samsung/qaboard
Author: Arthur Flam
Author-email: arthur.flam@samsung.com
License: Apache-2.0
Platform: UNKNOWN
Classifier: Development Status :: 3 - Alpha
Classifier: License :: OSI Approved :: Apache Software License
Classifier: Environment :: Console
Classifier: Programming Language :: Python :: 3
Classifier: Programming Language :: Python :: 3.7
Classifier: Topic :: Scientific/Engineering
Classifier: Topic :: Software Development :: Libraries
Classifier: Topic :: Software Development :: Quality Assurance
Requires-Python: >=3.7
Requires-Dist: click (>=7.0)
Requires-Dist: rich
Requires-Dist: requests
Requires-Dist: simplejson
Requires-Dist: pyyaml
Requires-Dist: joblib
Requires-Dist: sklearn
Requires-Dist: scikit-optimize
Provides-Extra: dev
Requires-Dist: flake8 ; extra == 'dev'
Requires-Dist: green ; extra == 'dev'
Requires-Dist: mypy ; extra == 'dev'
Requires-Dist: types-PyYAML ; extra == 'dev'
Requires-Dist: types-simplejson ; extra == 'dev'
Requires-Dist: types-requests ; extra == 'dev'
Requires-Dist: types-setuptools ; extra == 'dev'
